{
    "name": "My Workout Planner",
    "days": [
        {
            "exercises": [],
            "day": "Monday"
        },
        {
            "exercises": [{
                "sets": [],
                "muscleGroup": "Legs",
                "name": "Bar Squat"
            }],
            "day": "Tuesday"
        },
        {
            "exercises": [],
            "day": "Wednesday"
        },
        {
            "exercises": [],
            "day": "Thursday"
        },
        {
            "exercises": [],
            "day": "Friday"
        },
        {
            "exercises": [],
            "day": "Saturday"
        },
        {
            "exercises": [],
            "day": "Sunday"
        }
    ]
}